perflint/__init__.py
perflint/__main__.py
perflint/comprehension_checker.py
perflint/for_loop_checker.py
perflint/list_checker.py
perflint-0.8.1.dist-info/entry_points.txt
perflint-0.8.1.dist-info/LICENSE
perflint-0.8.1.dist-info/WHEEL
perflint-0.8.1.dist-info/METADATA
perflint-0.8.1.dist-info/RECORD
