Metadata-Version: 2.1
Name: perflint
Version: 0.8.1
Summary: Pylint extension with performance anti-patterns
Author: Anthony Shaw
Requires-Python: >=3.8
Classifier: License :: OSI Approved :: MIT License
Requires-Dist: pylint >=3.0.0,<4.0.0
Project-URL: Home, https://github.com/tonybaloney/perflint
